snakemake_wfcommons/__init__.py
snakemake_wfcommons-0.1.0.data/scripts/wfcommons-converter
snakemake_wfcommons-0.1.0.dist-info/LICENSE
snakemake_wfcommons-0.1.0.dist-info/METADATA
snakemake_wfcommons-0.1.0.dist-info/WHEEL
snakemake_wfcommons-0.1.0.dist-info/top_level.txt
snakemake_wfcommons-0.1.0.dist-info/RECORD
