Metadata-Version: 2.2
Name: snakemake_wfcommons
Version: 0.1.0
Summary: Python tool to convert Snakemake metadata to wfcommons single JSON files
Home-page: https://github.com/tud-zih-tools/snakemake-wfcommons
Project-URL: Homepage, https://github.com/tud-zih-tools/snakemake-wfcommons
Project-URL: Issues, https://github.com/tud-zih-tools/snakemake-wfcommons/issues
Classifier: Programming Language :: Python :: 3
Classifier: Development Status :: 3 - Alpha
Classifier: License :: OSI Approved :: BSD License
Requires-Python: >=3.9
License-File: LICENSE
Requires-Dist: wfcommons==1.0
Requires-Dist: snakemake
Dynamic: home-page
